{
  "$schema" : "http://json-schema.org/draft-07/schema#",
  "type" : "object",
  "properties" : {
    "averageDaysCriticalFindingsRemainUnpatchedPastYear" : {
      "type" : "number"
    },
    "averageDaysFindingsRemainUnpatchedPastYear" : {
      "type" : "number"
    },
    "averageDaysHighFindingsRemainUnpatchedPastYear" : {
      "type" : "number"
    },
    "averageDaysLowFindingsRemainUnpatchedPastYear" : {
      "type" : "number"
    },
    "averageDaysMediumFindingsRemainUnpatchedPastYear" : {
      "type" : "number"
    },
    "averagePatchEfficacyPastYear" : {
      "type" : "number"
    },
    "deltaRpsScore" : {
      "type" : "number"
    },
    "edits" : {
      "type" : "array",
      "items" : {
        "type" : "object",
        "properties" : {
          "after" : {
            "type" : "string"
          },
          "before" : {
            "type" : "string"
          },
          "dataSource" : {
            "type" : "object",
            "properties" : {
              "name" : {
                "type" : "string"
              },
              "namespace" : {
                "type" : "string"
              },
              "qualifiers" : {
                "type" : "object"
              },
              "scheme" : {
                "type" : "string"
              },
              "subpath" : {
                "type" : "string"
              },
              "type" : {
                "type" : "string"
              },
              "version" : {
                "type" : "string"
              }
            }
          },
          "editType" : {
            "type" : "string",
            "enum" : [ "CREATE", "UPDATE", "DELETE" ]
          },
          "isPfRecommendedEdit" : {
            "type" : "boolean"
          },
          "isSameEdit" : {
            "type" : "boolean"
          }
        }
      }
    },
    "eventDateTime" : {
      "type" : "string"
    },
    "forecastMaturityDate" : {
      "type" : "string"
    },
    "numberCriticalFindings" : {
      "type" : "number"
    },
    "numberCriticalFindingsAvoidedByPatchingPastYear" : {
      "type" : "number"
    },
    "numberDifferetPatches" : {
      "type" : "number"
    },
    "numberFindings" : {
      "type" : "number"
    },
    "numberFindingsAvoidedByPatchingPastYear" : {
      "type" : "number"
    },
    "numberHighFindings" : {
      "type" : "number"
    },
    "numberHighFindingsAvoidedByPatchingPastYear" : {
      "type" : "number"
    },
    "numberLowFindings" : {
      "type" : "number"
    },
    "numberLowFindingsAvoidedByPatchingPastYear" : {
      "type" : "number"
    },
    "numberMediumFindings" : {
      "type" : "number"
    },
    "numberMediumFindingsAvoidedByPatchingPastYear" : {
      "type" : "number"
    },
    "numberOfDownlevelPackages" : {
      "type" : "number"
    },
    "numberOfDownlevelPackagesMajor" : {
      "type" : "number"
    },
    "numberOfDownlevelPackagesMinor" : {
      "type" : "number"
    },
    "numberOfDownlevelPackagesPatch" : {
      "type" : "number"
    },
    "numberOfStalePackages" : {
      "type" : "number"
    },
    "numberOfStalePackagesOneYear" : {
      "type" : "number"
    },
    "numberOfStalePackagesPatchOneYearSixMonths" : {
      "type" : "number"
    },
    "numberOfStalePackagesPatchTwoYears" : {
      "type" : "number"
    },
    "numberOfStalePackagesSixMonths" : {
      "type" : "number"
    },
    "numberPackages" : {
      "type" : "number"
    },
    "numberPackagesWithCriticalFindings" : {
      "type" : "number"
    },
    "numberPackagesWithFindings" : {
      "type" : "number"
    },
    "numberPackagesWithHighFindings" : {
      "type" : "number"
    },
    "numberPackagesWithLowFindings" : {
      "type" : "number"
    },
    "numberPackagesWithMediumFindings" : {
      "type" : "number"
    },
    "numberPatchFoxPatches" : {
      "type" : "number"
    },
    "numberPatches" : {
      "type" : "number"
    },
    "numberSamePatches" : {
      "type" : "number"
    }
  }
}